carson_living/__init__.py
carson_living/auth.py
carson_living/carson.py
carson_living/carson_entities.py
carson_living/const.py
carson_living/eagleeye.py
carson_living/eagleeye_entities.py
carson_living/entities.py
carson_living/error.py
carson_living/util.py
carson_living-0.0.5.dist-info/LICENSE
carson_living-0.0.5.dist-info/METADATA
carson_living-0.0.5.dist-info/WHEEL
carson_living-0.0.5.dist-info/top_level.txt
carson_living-0.0.5.dist-info/RECORD
