Metadata-Version: 1.2
Name: carson_living
Version: 0.0.5
Summary: A Python library to communicate with Carson Living Residences (https://www.carson.live/)
Home-page: https://github.com/rado0x54/python-carson-living
Author: Martin Riedel
Author-email: web@riedel-it.de
License: Apache License 2.0
Keywords: carson living,virtual doorman,home automation
Platform: UNKNOWN
Classifier: Environment :: Other Environment
Classifier: Intended Audience :: Developers
Classifier: License :: OSI Approved :: Apache Software License
Classifier: Operating System :: OS Independent
Classifier: Programming Language :: Python
Classifier: Programming Language :: Python :: 2.7
Classifier: Programming Language :: Python :: 3.5
Classifier: Programming Language :: Python :: 3.6
Classifier: Programming Language :: Python :: 3.7
Classifier: Programming Language :: Python :: 3.8
Classifier: Programming Language :: Python :: 3.9
Classifier: Topic :: Home Automation
Classifier: Topic :: Software Development :: Libraries :: Python Modules
Requires-Python: >=2.7, !=3.0.*, !=3.1.*, !=3.2.*, !=3.3.*
